nicetypes/__init__.py
nicetypes/dicts.py
nicetypes/lists.py
nicetypes-0.4.0.dist-info/DESCRIPTION.rst
nicetypes-0.4.0.dist-info/LICENSE.txt
nicetypes-0.4.0.dist-info/METADATA
nicetypes-0.4.0.dist-info/RECORD
nicetypes-0.4.0.dist-info/WHEEL
nicetypes-0.4.0.dist-info/metadata.json
nicetypes-0.4.0.dist-info/top_level.txt
