Metadata-Version: 2.0
Name: nicetypes
Version: 0.4.0
Summary: Advanced types: UniqList and ImmutableDict
Home-page: https://github.com/tvuillemin/nicetypes
Author: Thibaut Vuillemin
Author-email: contact@thibautvuillemin.com
License: MIT
Keywords: class,attribute,boilerplate
Platform: UNKNOWN
Classifier: Development Status :: 5 - Production/Stable
Classifier: Intended Audience :: Developers
Classifier: Natural Language :: English
Classifier: License :: OSI Approved :: MIT License
Classifier: Operating System :: OS Independent
Classifier: Programming Language :: Python
Classifier: Programming Language :: Python :: 3
Classifier: Programming Language :: Python :: 3.4
Classifier: Programming Language :: Python :: 3.5
Classifier: Programming Language :: Python :: 3.6
Classifier: Programming Language :: Python :: Implementation :: CPython
Classifier: Programming Language :: Python :: Implementation :: PyPy
Classifier: Topic :: Software Development :: Libraries :: Python Modules
